pandas_wrapping/airtable.py
pandas_wrapping-0.0.3.dist-info/LICENSE
pandas_wrapping-0.0.3.dist-info/METADATA
pandas_wrapping-0.0.3.dist-info/WHEEL
pandas_wrapping-0.0.3.dist-info/entry_points.txt
pandas_wrapping-0.0.3.dist-info/top_level.txt
pandas_wrapping-0.0.3.dist-info/RECORD
