Metadata-Version: 2.1
Name: pandas-wrapping
Version: 0.0.3
Summary: A Python package for working with rest APIs
Home-page: https://github.com/renzobecerra/pandas-wrapping
Author: Renzo Becerra
Author-email: rbecerra@nameless.ai
License: MIT
Platform: UNKNOWN
Classifier: License :: OSI Approved :: MIT License
Classifier: Programming Language :: Python :: 3
Classifier: Programming Language :: Python :: 3.7
Requires-Dist: requests
Requires-Dist: pandas
